gated_block_dummy.v
`timescale 1ns / 1ps

module gated_block_dummy (
    input wire clk,
    input wire rst_n,
    input wire save_state,
    output reg ack_from_block
);
    
    reg [1:0] save_state_dly;

    always @(posedge clk or negedge rst_n) begin
        if (!rst_n) begin
            save_state_dly <= 2'b0;
            ack_from_block <= 1'b0;
        end else begin
            save_state_dly[0] <= save_state;
            save_state_dly[1] <= save_state_dly[0];
            
            if (save_state_dly[1] == 1'b1) ack_from_block <= 1'b1;
            else ack_from_block <= 1'b0;
        end
    end
endmodule

power_gating_controller.v
////////////////////////////////////////////////////////////////////////////////
//
// Module: power_gating_controller.v (Stable Version)
//
// Description: The simple, stable FSM controller. This logic is already
//              robust against redundant power-on requests by design.
//
////////////////////////////////////////////////////////////////////////////////
`timescale 1ns / 1ps

module power_gating_controller (
    // Control Inputs
    input wire clk,
    input wire rst_n,
    input wire power_on_req,
    input wire power_off_req,
    input wire ack_from_block,

    // Outputs to control the power-gated domain
    output reg isolate_en,
    output reg save_state,
    output reg restore_state,
    output reg power_switch_en,

    // Acknowledgment outputs to the system
    output reg power_on_ack,
    output reg power_off_ack
);

    // FSM State Definitions
    localparam [2:0] IDLE_OFF      = 3'b000;
    localparam [2:0] PWR_UP_SEQ    = 3'b001;
    localparam [2:0] WAIT_STABLE   = 3'b010;
    localparam [2:0] IDLE_ON       = 3'b011;
    localparam [2:0] PWR_DN_SEQ_1  = 3'b100;
    localparam [2:0] PWR_DN_SEQ_2  = 3'b101;
    localparam [2:0] PWR_DN_SEQ_3  = 3'b110;

    // State registers
    reg [2:0] current_state, next_state;
    reg [3:0] stable_counter;

    always @(posedge clk or negedge rst_n) begin
        if (!rst_n) current_state <= IDLE_OFF;
        else current_state <= next_state;
    end

    always @(posedge clk or negedge rst_n) begin
        if (!rst_n) stable_counter <= 0;
        else if (current_state == PWR_UP_SEQ) stable_counter <= 4'd10;
        else if (current_state == WAIT_STABLE && stable_counter > 0) stable_counter <= stable_counter - 1;
    end

    always @(*) begin
        next_state      = current_state;
        isolate_en      = 1'b1;
        save_state      = 1'b0;
        restore_state   = 1'b0;
        power_switch_en = 1'b1;
        power_on_ack    = 1'b0;
        power_off_ack   = 1'b0;

        case (current_state)
            IDLE_OFF: begin
                power_switch_en = 1'b0;
                if (power_on_req) next_state = PWR_UP_SEQ;
            end
            PWR_UP_SEQ: next_state = WAIT_STABLE;
            WAIT_STABLE: if (stable_counter == 0) begin
                restore_state = 1'b1;
                next_state = IDLE_ON;
            end
            IDLE_ON: begin
                isolate_en = 1'b0;
                power_on_ack = 1'b1;
                // NOTE: This logic correctly ignores power_on_req
                // and only acts on power_off_req.
                if (power_off_req) next_state = PWR_DN_SEQ_1;
            end
            PWR_DN_SEQ_1: next_state = PWR_DN_SEQ_2;
            PWR_DN_SEQ_2: begin
                save_state = 1'b1;
                if (ack_from_block) next_state = PWR_DN_SEQ_3;
            end
            PWR_DN_SEQ_3: begin
                power_switch_en = 1'b0;
                power_off_ack = 1'b1;
                next_state = IDLE_OFF;
            end
            default: next_state = IDLE_OFF;
        endcase
    end
endmodule

top.v
`timescale 1ns / 1ps

module top (
    input wire clk,
    input wire rst_n,
    input wire power_on_req,
    input wire power_off_req,
    input wire ack_from_block_tb,
    output wire isolate_en,
    output wire save_state,
    output wire restore_state,
    output wire power_switch_en,
    output wire power_on_ack,
    output wire power_off_ack
);

    wire ack_from_block_dummy;

    power_gating_controller pgc_inst (
        .clk(clk),
        .rst_n(rst_n),
        .power_on_req(power_on_req),
        .power_off_req(power_off_req),
        .ack_from_block(ack_from_block_tb),
        .isolate_en(isolate_en),
        .save_state(save_state),
        .restore_state(restore_state),
        .power_switch_en(power_switch_en),
        .power_on_ack(power_on_ack),
        .power_off_ack(power_off_ack)
    );

    gated_block_dummy dummy_inst (
        .clk(clk),
        .rst_n(rst_n),
        .save_state(save_state),
        .ack_from_block(ack_from_block_dummy)
    );
endmodule

tb_power_gating.v
`timescale 1ns / 1ps

module tb_power_gating;

    // DUT Interface
    reg clk;
    reg rst_n;
    reg power_on_req;
    reg power_off_req;
    reg ack_from_block_tb;
    wire isolate_en;
    wire save_state;
    wire restore_state;
    wire power_switch_en;
    wire power_on_ack;
    wire power_off_ack;

    // Metrics calculation
    integer total_simulation_cycles = 0;
    integer power_on_cycles = 0;
    real savings_percentage;

    // DUT Instantiation
    top uut (
        .clk(clk), .rst_n(rst_n), .power_on_req(power_on_req),
        .power_off_req(power_off_req), .ack_from_block_tb(ack_from_block_tb),
        .isolate_en(isolate_en), .save_state(save_state),
        .restore_state(restore_state), .power_switch_en(power_switch_en),
        .power_on_ack(power_on_ack), .power_off_ack(power_off_ack)
    );

    // Clock Generation
    initial forever #5 clk = ~clk;

    // Metrics Counter
    always @(posedge clk) begin
        if(rst_n) begin
            total_simulation_cycles = total_simulation_cycles + 1;
            if (power_switch_en) begin
                power_on_cycles = power_on_cycles + 1;
            end
        end
    end

    // Main Test Sequence
    initial begin
        $dumpfile("power_gating_metrics.vcd");
        $dumpvars(0, tb_power_gating);
        clk = 0; rst_n = 0; power_on_req = 0; power_off_req = 0; ack_from_block_tb = 0;
        #20; rst_n = 1;
        $display("[%0t ns] Reset released. System is in POWER_OFF state.", $time);

        // --- PHASE 1: Happy Path Operation ---
        #100;
        $display("\n--- PHASE 1: Running Happy Path Test ---");
        $display("[%0t ns] Asserting power_on_req.", $time);
        power_on_req = 1;
        @(posedge power_on_ack);
        power_on_req = 0;
        $display("[%0t ns] Power-up sequence complete (power_on_ack received).", $time);

        // --- PHASE 2: Redundant Request Robustness Check ---
        #50;
        $display("\n--- PHASE 2: Running Redundant Request Test ---");
        $display("[%0t ns] Sending redundant power_on_req while already ON...", $time);
        power_on_req = 1;
        #20; // Hold the request for a few cycles
        power_on_req = 0;

        // SELF-CHECK: The state should NOT have changed from IDLE_ON (3'b011)
        if (uut.pgc_inst.current_state === 3'b011) begin
            $display("PASS: Controller correctly ignored the redundant request.");
        end else begin
            $error("FAIL: Controller state was disturbed by the redundant request!");
        end
        
        // --- PHASE 3: Continue Happy Path to Power Down ---
        #430; // Remainder of the active period
        $display("\n--- PHASE 3: Continuing to Power-Down ---");
        $display("[%0t ns] Asserting power_off_req.", $time);
        power_off_req = 1;
        @(posedge save_state);
        #10 ack_from_block_tb = 1;
        @(posedge power_off_ack);
        power_off_req = 0;
        ack_from_block_tb = 0;
        $display("[%0t ns] Power-down sequence complete (power_off_ack received).", $time);
        
        #1000;
        
        // --- FINAL REPORT ---
        $display("\n----------------- SIMULATION COMPLETE -----------------\n");
        savings_percentage = (1.0 - ($itor(power_on_cycles) / $itor(total_simulation_cycles))) * 100.0;
        $display("           PERFORMANCE METRICS");
        $display("--------------------------------------------------");
        $display("Total Simulation Duration   : %0d clock cycles", total_simulation_cycles);
        $display("Cycles in Power-ON State    : %0d clock cycles", power_on_cycles);
        $display("");
        $display("--> Leakage Energy Saved    : %0.2f %%", savings_percentage);
        $display("--------------------------------------------------");
        $finish;
    end
endmodule

power_gating_metrics.vcd
$date
	Sat Sep 06 20:10:08 2025
$end
$version
	Icarus Verilog
$end
$timescale
	1ps
$end
$scope module tb_power_gating $end
$var wire 1 ! isolate_en $end
$var wire 1 " power_off_ack $end
$var wire 1 # power_on_ack $end
$var wire 1 $ power_switch_en $end
$var wire 1 % restore_state $end
$var wire 1 & save_state $end
$var reg 1 ' ack_from_block_tb $end
$var reg 1 ( clk $end
$var reg 1 ) power_off_req $end
$var integer 32 * power_on_cycles [31:0] $end
$var reg 1 + power_on_req $end
$var reg 1 , rst_n $end
$var integer 32 - total_simulation_cycles [31:0] $end
$var real 1 . savings_percentage $end
$scope module uut $end
$var wire 1 / ack_from_block_dummy $end
$var wire 1 0 ack_from_block_tb $end
$var wire 1 1 clk $end
$var wire 1 ! isolate_en $end
$var wire 1 " power_off_ack $end
$var wire 1 2 power_off_req $end
$var wire 1 # power_on_ack $end
$var wire 1 3 power_on_req $end
$var wire 1 $ power_switch_en $end
$var wire 1 % restore_state $end
$var wire 1 4 rst_n $end
$var wire 1 & save_state $end
$scope module pgc_inst $end
$var wire 1 0 ack_from_block $end
$var wire 1 1 clk $end
$var wire 1 2 power_off_req $end
$var wire 1 3 power_on_req $end
$var wire 1 4 rst_n $end
$var reg 3 5 current_state [2:0] $end
$var reg 1 6 isolate_en $end
$var reg 3 7 next_state [2:0] $end
$var reg 1 8 power_off_ack $end
$var reg 1 9 power_on_ack $end
$var reg 1 : power_switch_en $end
$var reg 1 ; restore_state $end
$var reg 1 < save_state $end
$var reg 4 = stable_counter [3:0] $end
$upscope $end
$scope module dummy_inst $end
$var wire 1 1 clk $end
$var wire 1 4 rst_n $end
$var wire 1 & save_state $end
$var reg 1 > ack_from_block $end
$var reg 2 ? save_state_dly [1:0] $end
$upscope $end
$upscope $end
$upscope $end
$enddefinitions $end
#0
$dumpvars
b0 ?
0>
b0 =
0<
0;
0:
09
08
b0 7
16
b0 5
04
03
02
01
00
0/
r0 .
b0 -
0,
0+
b0 *
0)
0(
0'
0&
0%
0$
0#
0"
1!
$end
#5000
1(
11
#10000
0(
01
#15000
1(
11
#20000
0(
01
1,
14
#25000
b0 ?
b1 -
1(
11
#30000
0(
01
#35000
b0 ?
b10 -
1(
11
#40000
0(
01
#45000
b0 ?
b11 -
1(
11
#50000
0(
01
#55000
b0 ?
b100 -
1(
11
#60000
0(
01
#65000
b0 ?
b101 -
1(
11
#70000
0(
01
#75000
b0 ?
b110 -
1(
11
#80000
0(
01
#85000
b0 ?
b111 -
1(
11
#90000
0(
01
#95000
b0 ?
b1000 -
1(
11
#100000
0(
01
#105000
b0 ?
b1001 -
1(
11
#110000
0(
01
#115000
b0 ?
b1010 -
1(
11
#120000
b1 7
0:
0$
0(
01
1+
13
#125000
b10 7
1:
1$
b0 ?
b1 5
b1011 -
1(
11
#130000
0(
01
#135000
b10 5
b1010 =
b0 ?
b1 *
b1100 -
1(
11
#140000
0(
01
#145000
b0 ?
b1001 =
b10 *
b1101 -
1(
11
#150000
0(
01
#155000
b1000 =
b0 ?
b11 *
b1110 -
1(
11
#160000
0(
01
#165000
b0 ?
b111 =
b100 *
b1111 -
1(
11
#170000
0(
01
#175000
b110 =
b0 ?
b101 *
b10000 -
1(
11
#180000
0(
01
#185000
b0 ?
b101 =
b110 *
b10001 -
1(
11
#190000
0(
01
#195000
b100 =
b0 ?
b111 *
b10010 -
1(
11
#200000
0(
01
#205000
b0 ?
b11 =
b1000 *
b10011 -
1(
11
#210000
0(
01
#215000
b10 =
b0 ?
b1001 *
b10100 -
1(
11
#220000
0(
01
#225000
b0 ?
b1 =
b1010 *
b10101 -
1(
11
#230000
0(
01
#235000
b11 7
1;
1%
b0 =
b0 ?
b1011 *
b10110 -
1(
11
#240000
0(
01
#245000
0+
03
19
1#
06
0!
0;
0%
b0 ?
b11 5
b1100 *
b10111 -
1(
11
#250000
0(
01
#255000
b0 ?
b1101 *
b11000 -
1(
11
#260000
0(
01
#265000
b0 ?
b1110 *
b11001 -
1(
11
#270000
0(
01
#275000
b0 ?
b1111 *
b11010 -
1(
11
#280000
0(
01
#285000
b0 ?
b10000 *
b11011 -
1(
11
#290000
0(
01
#295000
b0 ?
b10001 *
b11100 -
19
1#
06
0!
1(
11
1+
13
#300000
0(
01
#305000
b0 ?
b10010 *
b11101 -
1(
11
#310000
0(
01
#315000
b0 ?
b10011 *
b11110 -
19
1#
06
0!
1(
11
0+
03
#320000
0(
01
#325000
b0 ?
b10100 *
b11111 -
1(
11
#330000
0(
01
#335000
b0 ?
b10101 *
b100000 -
1(
11
#340000
0(
01
#345000
b0 ?
b10110 *
b100001 -
1(
11
#350000
0(
01
#355000
b0 ?
b10111 *
b100010 -
1(
11
#360000
0(
01
#365000
b0 ?
b11000 *
b100011 -
1(
11
#370000
0(
01
#375000
b0 ?
b11001 *
b100100 -
1(
11
#380000
0(
01
#385000
b0 ?
b11010 *
b100101 -
1(
11
#390000
0(
01
#395000
b0 ?
b11011 *
b100110 -
1(
11
#400000
0(
01
#405000
b0 ?
b11100 *
b100111 -
1(
11
#410000
0(
01
#415000
b0 ?
b11101 *
b101000 -
1(
11
#420000
0(
01
#425000
b0 ?
b11110 *
b101001 -
1(
11
#430000
0(
01
#435000
b0 ?
b11111 *
b101010 -
1(
11
#440000
0(
01
#445000
b0 ?
b100000 *
b101011 -
1(
11
#450000
0(
01
#455000
b0 ?
b100001 *
b101100 -
1(
11
#460000
0(
01
#465000
b0 ?
b100010 *
b101101 -
1(
11
#470000
0(
01
#475000
b0 ?
b100011 *
b101110 -
1(
11
#480000
0(
01
#485000
b0 ?
b100100 *
b101111 -
1(
11
#490000
0(
01
#495000
b0 ?
b100101 *
b110000 -
1(
11
#500000
0(
01
#505000
b0 ?
b100110 *
b110001 -
1(
11
#510000
0(
01
#515000
b0 ?
b100111 *
b110010 -
1(
11
#520000
0(
01
#525000
b0 ?
b101000 *
b110011 -
1(
11
#530000
0(
01
#535000
b0 ?
b101001 *
b110100 -
1(
11
#540000
0(
01
#545000
b0 ?
b101010 *
b110101 -
1(
11
#550000
0(
01
#555000
b0 ?
b101011 *
b110110 -
1(
11
#560000
0(
01
#565000
b0 ?
b101100 *
b110111 -
1(
11
#570000
0(
01
#575000
b0 ?
b101101 *
b111000 -
1(
11
#580000
0(
01
#585000
b0 ?
b101110 *
b111001 -
1(
11
#590000
0(
01
#595000
b0 ?
b101111 *
b111010 -
1(
11
#600000
0(
01
#605000
b0 ?
b110000 *
b111011 -
1(
11
#610000
0(
01
#615000
b0 ?
b110001 *
b111100 -
1(
11
#620000
0(
01
#625000
b0 ?
b110010 *
b111101 -
1(
11
#630000
0(
01
#635000
b0 ?
b110011 *
b111110 -
1(
11
#640000
0(
01
#645000
b0 ?
b110100 *
b111111 -
1(
11
#650000
0(
01
#655000
b0 ?
b110101 *
b1000000 -
1(
11
#660000
0(
01
#665000
b0 ?
b110110 *
b1000001 -
1(
11
#670000
0(
01
#675000
b0 ?
b110111 *
b1000010 -
1(
11
#680000
0(
01
#685000
b0 ?
b111000 *
b1000011 -
1(
11
#690000
0(
01
#695000
b0 ?
b111001 *
b1000100 -
1(
11
#700000
0(
01
#705000
b0 ?
b111010 *
b1000101 -
1(
11
#710000
0(
01
#715000
b0 ?
b111011 *
b1000110 -
1(
11
#720000
0(
01
#725000
b0 ?
b111100 *
b1000111 -
1(
11
#730000
0(
01
#735000
b0 ?
b111101 *
b1001000 -
1(
11
#740000
0(
01
#745000
b0 ?
b100 5
b111110 *
b1001001 -
b101 7
09
0#
16
1!
1(
11
1)
12
#750000
0(
01
#755000
1<
1&
b101 5
b0 ?
b111111 *
b1001010 -
1(
11
#760000
0(
01
#765000
0)
02
18
1"
0:
0$
b1 ?
b110 5
b1000000 *
b1001011 -
b0 7
0<
0&
1(
11
0'
00
#770000
0(
01
#775000
08
0"
0:
0$
b0 5
b10 ?
b1001100 -
1(
11
#780000
0(
01
#785000
1>
1/
b0 ?
b1001101 -
1(
11
#790000
0(
01
#795000
0>
0/
b0 ?
b1001110 -
1(
11
#800000
0(
01
#805000
b0 ?
b1001111 -
1(
11
#810000
0(
01
#815000
b0 ?
b1010000 -
1(
11
#820000
0(
01
#825000
b0 ?
b1010001 -
1(
11
#830000
0(
01
#835000
b0 ?
b1010010 -
1(
11
#840000
0(
01
#845000
b0 ?
b1010011 -
1(
11
#850000
0(
01
#855000
b0 ?
b1010100 -
1(
11
#860000
0(
01
#865000
b0 ?
b1010101 -
1(
11
#870000
0(
01
#875000
b0 ?
b1010110 -
1(
11
#880000
0(
01
#885000
b0 ?
b1010111 -
1(
11
#890000
0(
01
#895000
b0 ?
b1011000 -
1(
11
#900000
0(
01
#905000
b0 ?
b1011001 -
1(
11
#910000
0(
01
#915000
b0 ?
b1011010 -
1(
11
#920000
0(
01
#925000
b0 ?
b1011011 -
1(
11
#930000
0(
01
#935000
b0 ?
b1011100 -
1(
11
#940000
0(
01
#945000
b0 ?
b1011101 -
1(
11
#950000
0(
01
#955000
b0 ?
b1011110 -
1(
11
#960000
0(
01
#965000
b0 ?
b1011111 -
1(
11
#970000
0(
01
#975000
b0 ?
b1100000 -
1(
11
#980000
0(
01
#985000
b0 ?
b1100001 -
1(
11
#990000
0(
01
#995000
b0 ?
b1100010 -
1(
11
#1000000
0(
01
#1005000
b0 ?
b1100011 -
1(
11
#1010000
0(
01
#1015000
b0 ?
b1100100 -
1(
11
#1020000
0(
01
#1025000
b0 ?
b1100101 -
1(
11
#1030000
0(
01
#1035000
b0 ?
b1100110 -
1(
11
#1040000
0(
01
#1045000
b0 ?
b1100111 -
1(
11
#1050000
0(
01
#1055000
b0 ?
b1101000 -
1(
11
#1060000
0(
01
#1065000
b0 ?
b1101001 -
1(
11
#1070000
0(
01
#1075000
b0 ?
b1101010 -
1(
11
#1080000
0(
01
#1085000
b0 ?
b1101011 -
1(
11
#1090000
0(
01
#1095000
b0 ?
b1101100 -
1(
11
#1100000
0(
01
#1105000
b0 ?
b1101101 -
1(
11
#1110000
0(
01
#1115000
b0 ?
b1101110 -
1(
11
#1120000
0(
01
#1125000
b0 ?
b1101111 -
1(
11
#1130000
0(
01
#1135000
b0 ?
b1110000 -
1(
11
#1140000
0(
01
#1145000
b0 ?
b1110001 -
1(
11
#1150000
0(
01
#1155000
b0 ?
b1110010 -
1(
11
#1160000
0(
01
#1165000
b0 ?
b1110011 -
1(
11
#1170000
0(
01
#1175000
b0 ?
b1110100 -
1(
11
#1180000
0(
01
#1185000
b0 ?
b1110101 -
1(
11
#1190000
0(
01
#1195000
b0 ?
b1110110 -
1(
11
#1200000
0(
01
#1205000
b0 ?
b1110111 -
1(
11
#1210000
0(
01
#1215000
b0 ?
b1111000 -
1(
11
#1220000
0(
01
#1225000
b0 ?
b1111001 -
1(
11
#1230000
0(
01
#1235000
b0 ?
b1111010 -
1(
11
#1240000
0(
01
#1245000
b0 ?
b1111011 -
1(
11
#1250000
0(
01
#1255000
b0 ?
b1111100 -
1(
11
#1260000
0(
01
#1265000
b0 ?
b1111101 -
1(
11
#1270000
0(
01
#1275000
b0 ?
b1111110 -
1(
11
#1280000
0(
01
#1285000
b0 ?
b1111111 -
1(
11
#1290000
0(
01
#1295000
b0 ?
b10000000 -
1(
11
#1300000
0(
01
#1305000
b0 ?
b10000001 -
1(
11
#1310000
0(
01
#1315000
b0 ?
b10000010 -
1(
11
#1320000
0(
01
#1325000
b0 ?
b10000011 -
1(
11
#1330000
0(
01
#1335000
b0 ?
b10000100 -
1(
11
#1340000
0(
01
#1345000
b0 ?
b10000101 -
1(
11
#1350000
0(
01
#1355000
b0 ?
b10000110 -
1(
11
#1360000
0(
01
#1365000
b0 ?
b10000111 -
1(
11
#1370000
0(
01
#1375000
b0 ?
b10001000 -
1(
11
#1380000
0(
01
#1385000
b0 ?
b10001001 -
1(
11
#1390000
0(
01
#1395000
b0 ?
b10001010 -
1(
11
#1400000
0(
01
#1405000
b0 ?
b10001011 -
1(
11
#1410000
0(
01
#1415000
b0 ?
b10001100 -
1(
11
#1420000
0(
01
#1425000
b0 ?
b10001101 -
1(
11
#1430000
0(
01
#1435000
b0 ?
b10001110 -
1(
11
#1440000
0(
01
#1445000
b0 ?
b10001111 -
1(
11
#1450000
0(
01
#1455000
b0 ?
b10010000 -
1(
11
#1460000
0(
01
#1465000
b0 ?
b10010001 -
1(
11
#1470000
0(
01
#1475000
b0 ?
b10010010 -
1(
11
#1480000
0(
01
#1485000
b0 ?
b10010011 -
1(
11
#1490000
0(
01
#1495000
b0 ?
b10010100 -
1(
11
#1500000
0(
01
#1505000
b0 ?
b10010101 -
1(
11
#1510000
0(
01
#1515000
b0 ?
b10010110 -
1(
11
#1520000
0(
01
#1525000
b0 ?
b10010111 -
1(
11
#1530000
0(
01
#1535000
b0 ?
b10011000 -
1(
11
#1540000
0(
01
#1545000
b0 ?
b10011001 -
1(
11
#1550000
0(
01
#1555000
b0 ?
b10011010 -
1(
11
#1560000
0(
01
#1565000
b0 ?
b10011011 -
1(
11
#1570000
0(
01
#1575000
b0 ?
b10011100 -
1(
11
#1580000
0(
01
#1585000
b0 ?
b10011101 -
1(
11
#1590000
0(
01
#1595000
b0 ?
b10011110 -
1(
11
#1600000
0(
01
#1605000
b0 ?
b10011111 -
1(
11
#1610000
0(
01
#1615000
b0 ?
b10100000 -
1(
11
#1620000
0(
01
#1625000
b0 ?
b10100001 -
1(
11
#1630000
0(
01
#1635000
b0 ?
b10100010 -
1(
11
#1640000
0(
01
#1645000
b0 ?
b10100011 -
1(
11
#1650000
0(
01
#1655000
b0 ?
b10100100 -
1(
11
#1660000
0(
01
#1665000
b0 ?
b10100101 -
1(
11
#1670000
0(
01
#1675000
b0 ?
b10100110 -
1(
11
#1680000
0(
01
#1685000
b0 ?
b10100111 -
1(
11
#1690000
0(
01
#1695000
b0 ?
b10101000 -
1(
11
#1700000
0(
01
#1705000
b0 ?
b10101001 -
1(
11
#1710000
0(
01
#1715000
b0 ?
b10101010 -
1(
11
#1720000
0(
01
#1725000
b0 ?
b10101011 -
1(
11
#1730000
0(
01
#1735000
b0 ?
b10101100 -
1(
11
#1740000
0(
01
#1745000
b0 ?
b10101101 -
1(
11
#1750000
0(
01
#1755000
b0 ?
b10101110 -
1(
11
#1760000
0(
01
#1765000
b0 ?
b10101111 -
1(
11
r63.2183908045977 .
